py_xel/__init__.py
py_xel/functions.py
py_xel-0.1.0.dist-info/METADATA
py_xel-0.1.0.dist-info/WHEEL
py_xel-0.1.0.dist-info/top_level.txt
py_xel-0.1.0.dist-info/RECORD
